tests/test_tokenizer.py
tigrigna_nlp/__init__.py
tigrigna_nlp/normalizer.py
tigrigna_nlp/tokenizer.json
tigrigna_nlp/tokenizer.py
tigrigna_nlp-0.1.0.dist-info/licenses/LICENSE
tigrigna_nlp-0.1.0.dist-info/METADATA
tigrigna_nlp-0.1.0.dist-info/WHEEL
tigrigna_nlp-0.1.0.dist-info/top_level.txt
tigrigna_nlp-0.1.0.dist-info/RECORD
