Metadata-Version: 2.4
Name: tigrigna-nlp
Version: 0.1.0
Summary: The first complete Tigrigna (ትግርኛ) NLP toolkit
Author-email: Haille <hailishmit@gmail.com>
License: MIT
Project-URL: Homepage, https://github.com/haile21/tigrigna-nlp
Project-URL: Repository, https://github.com/haile21/tigrigna-nlp
Project-URL: Issues, https://github.com/haile21/tigrigna-nlp/issues
Keywords: tigrigna,tigrinya,nlp,geez,eritrea,tigray,tigrai,ethiopia,african-nlp,low-resource,natural-language-processing
Classifier: Programming Language :: Python :: 3
Classifier: License :: OSI Approved :: MIT License
Classifier: Operating System :: OS Independent
Classifier: Intended Audience :: Developers
Classifier: Intended Audience :: Science/Research
Classifier: Topic :: Scientific/Engineering :: Artificial Intelligence
Classifier: Topic :: Text Processing :: Linguistic
Requires-Python: >=3.8
License-File: LICENSE
Requires-Dist: tokenizers>=0.19.0
Dynamic: license-file
